vamos/__init__.py
vamos/env.py
vamos/registration.py
vamos/environments/__init__.py
vamos/environments/brax/__init__.py
vamos/environments/classic_control/__init__.py
vamos/environments/classic_control/acrobot.py
vamos/environments/classic_control/cartpole.py
vamos/environments/classic_control/mountain_car.py
vamos/environments/classic_control/pendulum.py
vamos/environments/minatar/__init__.py
vamos/environments/minatar/asterix.py
vamos/environments/minatar/breakout.py
vamos/environments/minatar/freeway.py
vamos/environments/minatar/seaquest.py
vamos/environments/minatar/space_invaders.py
vamos/environments/misc/__init__.py
vamos/environments/misc/atari.py
vamos/environments/misc/craftax.py
vamos/environments/misc/four_rooms.py
vamos/environments/pgx/__init__.py
vamos/spaces/__init__.py
vamos/spaces/array.py
vamos/spaces/dict.py
vamos/spaces/scalar.py
vamos/spaces/space.py
vamos/utils/__init__.py
vamos/utils/performance.py
vamos/utils/rollout.py
vamos/utils/verify.py
vamos/vector/__init__.py
vamos/vector/pmap_vector_env.py
vamos/vector/vector_env.py
vamos/vector/vmap_vector_env.py
vamos/wrappers/__init__.py
vamos/wrappers/stop_gradient.py
vamos/wrappers/time_limit.py
vamos/wrappers/video_episode.py
vamos/wrappers/vector/__init__.py
vamos/wrappers/vector/human_rendering.py
vamos/wrappers/vector/record_episode_statistics.py
vamos_rl-0.1.0.dist-info/METADATA
vamos_rl-0.1.0.dist-info/WHEEL
vamos_rl-0.1.0.dist-info/top_level.txt
vamos_rl-0.1.0.dist-info/RECORD
