Metadata-Version: 2.4
Name: vamos-rl
Version: 0.1.0
Summary: An API for JAX-based Reinforcement Learning Environments
Author: Mark Towers
License: MIT License
Keywords: Reinforcement Learning,game,RL,AI,Vamos
Classifier: Development Status :: 5 - Production/Stable
Classifier: License :: OSI Approved :: MIT License
Classifier: Programming Language :: Python :: 3
Classifier: Programming Language :: Python :: 3.10
Classifier: Programming Language :: Python :: 3.11
Classifier: Programming Language :: Python :: 3.12
Classifier: Programming Language :: Python :: 3.13
Classifier: Intended Audience :: Science/Research
Classifier: Topic :: Scientific/Engineering :: Artificial Intelligence
Requires-Python: >=3.10
Requires-Dist: jax
Requires-Dist: chex
Requires-Dist: flax
